unittest_extensions/__init__.py
unittest_extensions/case.py
unittest_extensions/decorator.py
unittest_extensions/error.py
unittest_extensions-0.4.0.dist-info/licenses/LICENSE
unittest_extensions-0.4.0.dist-info/METADATA
unittest_extensions-0.4.0.dist-info/WHEEL
unittest_extensions-0.4.0.dist-info/top_level.txt
unittest_extensions-0.4.0.dist-info/RECORD
