Metadata-Version: 2.4
Name: unittest-extensions
Version: 0.4.0
Summary: Extension of Python's standard unittest library
Author-email: Maximos Nikiforakis <nikiforos@live.co.uk>
License: MIT
Project-URL: Homepage, https://github.com/Maxcode123/unittest-extensions
Project-URL: Documentation, https://maxcode123.github.io/unittest-extensions/
Project-URL: Issues, https://github.com/Maxcode123/unittest-extensions/issues
Classifier: Programming Language :: Python
Classifier: Programming Language :: Python :: 3
Classifier: Programming Language :: Python :: 3.8
Classifier: Programming Language :: Python :: 3.9
Classifier: Programming Language :: Python :: 3.10
Classifier: Programming Language :: Python :: 3.11
Classifier: Programming Language :: Python :: 3.12
Classifier: Intended Audience :: Developers
Classifier: License :: OSI Approved :: MIT License
Classifier: Operating System :: OS Independent
Classifier: Topic :: Software Development :: Testing :: Unit
Classifier: Topic :: Software Development :: Testing :: BDD
Requires-Python: >=3.8
License-File: LICENSE
Dynamic: license-file
